profilelog/__init__.py
profilelog/middleware.py
profilelog_middleware-0.0.2.dist-info/DESCRIPTION.rst
profilelog_middleware-0.0.2.dist-info/METADATA
profilelog_middleware-0.0.2.dist-info/RECORD
profilelog_middleware-0.0.2.dist-info/WHEEL
profilelog_middleware-0.0.2.dist-info/metadata.json
profilelog_middleware-0.0.2.dist-info/top_level.txt
