Metadata-Version: 2.0
Name: profilelog-middleware
Version: 0.0.2
Summary: WSGI middleware for logging profiling data.
